prman/__init__.py
prman/__main__.py
prman/config.base.jsonc
prman/config.py
prman/main.py
prman/cli/__init__.py
prman/cli/argparsing.py
prman/cli/colorized_print.py
prman/cli/interaction.py
prman/git/__init__.py
prman/git/git_conventions.py
prman/git/git_interop.py
prman/gl/__init__.py
prman/gl/gitlab_conventions.py
prman/gl/gitlab_interop.py
prman-0.1.7.dist-info/LICENSE
prman-0.1.7.dist-info/METADATA
prman-0.1.7.dist-info/WHEEL
prman-0.1.7.dist-info/entry_points.txt
prman-0.1.7.dist-info/top_level.txt
prman-0.1.7.dist-info/RECORD
