Metadata-Version: 2.1
Name: prman
Version: 0.1.7
Summary: Command line tool for automatic GitLab PR creation.
Home-page: https://github.com/ilyalatt/prman
Author: Ilya Latushko
Author-email: ilyalatt@gmail.com
License: Unlicense
Platform: UNKNOWN
Requires-Python: >=3.7
Requires-Dist: requests (==2.23.0)
Requires-Dist: jstyleson (==0.0.2)
Requires-Dist: python-gitlab (==2.1.2)
Requires-Dist: chardet (==3.0.4)
Requires-Dist: pyrecord (==1.0.1)
Requires-Dist: idna (==2.9)
Requires-Dist: toolz (==0.10.0)
Requires-Dist: brigit (==1.3.0)
Requires-Dist: urllib3 (==1.25.8)
Requires-Dist: log-colorizer (==1.8.6)
Requires-Dist: colorama (==0.4.3)
Requires-Dist: docopt (==0.6.2)
Requires-Dist: certifi (==2019.11.28)
